{
    "data":[{"id":"98faa0f7-ccff-447c-a6fa-4cd4e0ba75e1","recordName":"Whitespot","creationDate":"2022-01-19","lastUpdated":"2021-12-29"},
{"id":"d66cb509-060e-4c5c-98c8-10ee08840e5a","recordName":"Lecidea","creationDate":"2021-11-24","lastUpdated":"2022-07-11"},
{"id":"0f19bcc6-3a03-4f02-9121-da7876a87021","recordName":"Santa","creationDate":"2022-08-05","lastUpdated":"2021-10-10"},
{"id":"dce1f9b5-ddeb-446b-8ca6-e5cd23191a8b","recordName":"Syzygium","creationDate":"2021-11-17","lastUpdated":"2021-11-30"},
{"id":"e35dc5f0-8fa5-4a28-ad9b-5d47fa66ff5d","recordName":"Dicranum Moss","creationDate":"2021-10-13","lastUpdated":"2022-03-13"},
{"id":"95fe65f9-de72-4c18-b2a2-793725f1c195","recordName":"Harrimanella","creationDate":"2021-09-26","lastUpdated":"2022-04-02"},
{"id":"dedc83a9-989f-4eaa-be3e-352433671d5e","recordName":"Eared Rockcress","creationDate":"2022-02-08","lastUpdated":"2022-08-30"},
{"id":"4317fd48-d986-4b3b-9c83-6287b1eeda02","recordName":"Comal Nakedwood","creationDate":"2021-10-07","lastUpdated":"2022-03-16"},
{"id":"41d64ab8-98a6-497d-b948-05a5ef96fe82","recordName":"Silky Deerweed","creationDate":"2022-01-11","lastUpdated":"2022-07-13"},
{"id":"b1c012a8-bef2-4118-bfc2-21d5a15c993a","recordName":"Loa Milkvetch","creationDate":"2022-06-25","lastUpdated":"2022-06-24"},
{"id":"1400da5e-9353-4618-9f04-bb5ae9dfb8d7","recordName":"Dotted Beaksedge","creationDate":"2022-08-12","lastUpdated":"2022-02-22"},
{"id":"efb00dbf-5163-4846-ae5c-3c4fd637a17b","recordName":"Bruised Lichen","creationDate":"2022-08-14","lastUpdated":"2022-06-15"},
{"id":"c5aa8e5e-c53b-4978-98b4-ea02e869dc60","recordName":"White Velvetleaf","creationDate":"2022-03-20","lastUpdated":"2022-03-27"},
{"id":"620b426f-c99d-4b14-94e7-9cf605e4993e","recordName":"Thickstem ","creationDate":"2021-12-10","lastUpdated":"2022-04-16"},
{"id":"b865fc10-0718-4c4e-89e1-4780bb96a083","recordName":"Melanorrhoea","creationDate":"2021-11-21","lastUpdated":"2021-09-22"},
{"id":"3d02b26f-3a91-4957-8ece-2f7f3acf1a1a","recordName":"Panhandle Spurge","creationDate":"2022-02-26","lastUpdated":"2022-01-22"},
{"id":"6281be91-16b4-45b8-aadd-e1a22c783d9f","recordName":"Sphagnum Dewberry","creationDate":"2022-03-05","lastUpdated":"2022-01-15"},
{"id":"4a572110-2046-4fbe-ba43-1a0cf7d50b61","recordName":"Withe","creationDate":"2022-09-05","lastUpdated":"2021-10-25"},
{"id":"14bb1c9b-543c-4820-9197-0969faea4e92","recordName":"El Yunque Jacanillo","creationDate":"2022-02-26","lastUpdated":"2022-05-13"},
{"id":"cd039159-543f-48a2-b9a4-ae6a8f642a2c","recordName":"Swamp Tickseed","creationDate":"2022-04-03","lastUpdated":"2022-09-11"},
{"id":"fbdd477d-89d1-426d-95fa-39036c691cff","recordName":"German-madwort","creationDate":"2022-06-18","lastUpdated":"2022-06-15"},
{"id":"70186df8-40dc-445e-9c36-338fb81f711f","recordName":"Guyanese Pepper","creationDate":"2022-08-27","lastUpdated":"2021-09-19"},
{"id":"791756b0-10e8-402d-b68c-a7c3df1c5c68","recordName":"Red Mountain Catchfly","creationDate":"2022-06-25","lastUpdated":"2022-02-06"},
{"id":"6417ae51-be24-4620-b65e-803d1601a0a4","recordName":"Longstem Sandwort","creationDate":"2022-04-30","lastUpdated":"2022-06-13"},
{"id":"f1485ed2-4db8-4939-9712-d7f49240c321","recordName":"Dwarf Groundcherry","creationDate":"2022-05-23","lastUpdated":"2022-04-28"},
{"id":"e0dfcb97-7705-4901-b801-21c0d8d09940","recordName":"Sibbaldiopsis","creationDate":"2022-06-20","lastUpdated":"2022-02-07"},
{"id":"9ab154ca-a9bb-40eb-a38c-59d99d71ba60","recordName":"Cucamonga Manroot","creationDate":"2021-12-11","lastUpdated":"2021-12-08"},
{"id":"14187798-84d1-4a42-95ce-7ac14b1d0f17","recordName":"Basketgrass","creationDate":"2022-04-27","lastUpdated":"2022-08-05"},
{"id":"88a383d5-85be-4e9c-b857-97b6e754c361","recordName":"Cat's Ear","creationDate":"2022-03-06","lastUpdated":"2022-06-07"},
{"id":"59d17588-d750-4bef-bfca-2ab48e9b73e4","recordName":"Cylindric Navel Lichen","creationDate":"2022-09-13","lastUpdated":"2021-11-04"},
{"id":"eb19fbfc-985c-4125-b80a-b41ff8b21452","recordName":"Evans' Beard Lichen","creationDate":"2021-12-30","lastUpdated":"2022-01-17"},
{"id":"1c2f3fef-d8ba-4eaa-8c65-cf2b08c195d4","recordName":"Sierra Gooseberry","creationDate":"2022-08-22","lastUpdated":"2022-07-05"},
{"id":"1985df7f-907a-4567-80e6-dfa53521c567","recordName":"Scalebud","creationDate":"2022-03-21","lastUpdated":"2022-08-21"},
{"id":"8da41a12-0ab2-4acf-893f-09819390c579","recordName":"Cithara Buckwheat","creationDate":"2022-04-06","lastUpdated":"2022-01-24"},
{"id":"09ff0cfb-1bc8-40fe-b136-c7643ebcfe5c","recordName":"Toano Milkvetch","creationDate":"2022-03-12","lastUpdated":"2021-10-16"},
{"id":"b9fa247f-65c2-46c5-8758-cfcce44641bd","recordName":"Yellow Necklacepod","creationDate":"2022-03-22","lastUpdated":"2022-04-06"},
{"id":"4c6abb90-d44e-4ed4-a971-cb14030c3269","recordName":"Timber Oatgrass","creationDate":"2022-03-30","lastUpdated":"2022-08-19"},
{"id":"18f79364-9d90-4731-a408-8f830c700633","recordName":"Toothed Clubmoss","creationDate":"2022-08-05","lastUpdated":"2022-08-02"},
{"id":"3fa7e8b6-5a03-4994-bb9b-460bcfe95585","recordName":"East ","creationDate":"2022-07-31","lastUpdated":"2022-01-13"},
{"id":"4ed0d93b-49ad-4686-a66e-91f58958e3ab","recordName":"Waianae ","creationDate":"2022-01-04","lastUpdated":"2022-08-19"},
{"id":"23c26131-d0fe-4321-83e1-47511d532bc0","recordName":"Narrow Strapfern","creationDate":"2021-10-13","lastUpdated":"2022-07-21"},
{"id":"5c747ad5-ac87-42b3-b459-3576b3b51346","recordName":"Pleuroziopsis Moss","creationDate":"2021-10-07","lastUpdated":"2022-04-10"},
{"id":"31ea6319-4697-4681-854a-bd60bee86da8","recordName":"Rushleaf Eryngo","creationDate":"2021-12-02","lastUpdated":"2022-08-29"},
{"id":"cf737e63-f94e-4e91-9618-b81d6734a9ed","recordName":"Solmsiella Moss","creationDate":"2021-10-02","lastUpdated":"2021-11-13"},
{"id":"fec80870-d483-4c65-a0d6-eea9cd9d2aeb","recordName":"Mock Vervain","creationDate":"2022-02-23","lastUpdated":"2021-11-11"},
{"id":"4ec3d703-7170-4b77-b581-bed3266b43ff","recordName":"Goosegrass","creationDate":"2021-09-22","lastUpdated":"2022-05-09"},
{"id":"eac5174c-2ed8-420d-b093-6d72fd6a0718","recordName":"Eared Coneflower","creationDate":"2022-02-24","lastUpdated":"2021-12-24"},
{"id":"96da9821-ce8d-4d26-abea-77c66550e8ec","recordName":"Sprengel's Sedge","creationDate":"2022-01-18","lastUpdated":"2021-11-27"},
{"id":"369bcc47-817f-4154-b06b-98c77a0a6c31","recordName":"Common Gardenia","creationDate":"2022-04-18","lastUpdated":"2022-02-13"},
{"id":"a6c068a0-6fd6-4c23-8f35-bb2fc6619276","recordName":"Ovate Goatgrass","creationDate":"2022-04-06","lastUpdated":"2022-03-18"}]
}